{"experiments":{"pref-feature-impact-study-for-enhanced-tracking-protec-release-72-80-bug-1606713":{"slug":"pref-feature-impact-study-for-enhanced-tracking-protec-release-72-80-bug-1606713","actionName":"PreferenceExperimentAction","branch":"treatment-branch","expired":true,"lastSeen":"2020-02-15T15:45:22.273Z","preferences":{"browser.search.param.google_channel_us":{"preferenceType":"string","preferenceValue":"tus2","preferenceBranchType":"default","previousPreferenceValue":null},"browser.search.param.google_channel_row":{"preferenceType":"string","preferenceValue":"trow2","preferenceBranchType":"default","previousPreferenceValue":null},"privacy.annotate_channels.strict_list.enabled":{"preferenceType":"boolean","preferenceValue":true,"preferenceBranchType":"default","previousPreferenceValue":false},"urlclassifier.trackingAnnotationTable.testEntries":{"preferenceType":"string","preferenceValue":"etp-experiment-1.dummytracker.org","preferenceBranchType":"default","previousPreferenceValue":null}},"experimentType":"exp","userFacingName":"ETP Level 2 study","userFacingDescription":"This study is examining the effects of Enhanced Tracking Protection Level 2.","enrollmentId":"8ff0c682-e09f-4233-b1c5-9b5beee2eb6f"}}}